ocs_ingester/__init__.py
ocs_ingester/archive.py
ocs_ingester/exceptions.py
ocs_ingester/ingester.py
ocs_ingester/scripts/__init__.py
ocs_ingester/scripts/ingest_frame.py
ocs_ingester/settings/__init__.py
ocs_ingester/settings/log_config.py
ocs_ingester/settings/settings.py
ocs_ingester/utils/__init__.py
ocs_ingester/utils/metrics.py
ocs_ingester-3.1.0.dist-info/LICENSE
ocs_ingester-3.1.0.dist-info/METADATA
ocs_ingester-3.1.0.dist-info/WHEEL
ocs_ingester-3.1.0.dist-info/entry_points.txt
ocs_ingester-3.1.0.dist-info/top_level.txt
ocs_ingester-3.1.0.dist-info/RECORD
