Metadata-Version: 2.1
Name: ocs-ingester
Version: 3.1.0
Summary: Ingest frames into the science archive of an observatory control system
Home-page: https://github.com/observatorycontrolsystem/ingester
Classifier: License :: OSI Approved :: GNU General Public License v3 (GPLv3)
Requires-Python: >=3.7
License-File: LICENSE
Requires-Dist: astropy
Requires-Dist: requests
Requires-Dist: boto3
Requires-Dist: ocs-archive ==0.4.0
Requires-Dist: python-dateutil
Requires-Dist: lcogt-logging
Requires-Dist: opentsdb-python-metrics >=0.2.0
Provides-Extra: tests
Requires-Dist: pytest ; extra == 'tests'
